scisbi/__init__.py
scisbi/base/__init__.py
scisbi/base/inference.py
scisbi/base/simulator.py
scisbi/base/summary_statistic.py
scisbi/base/workflow.py
scisbi/inference/ABC.py
scisbi/inference/ABCMCMC.py
scisbi/inference/ABCSMC.py
scisbi/inference/JANA.py
scisbi/inference/Simformer.py
scisbi/inference/__init__.py
scisbi/simulator/GRNSimulator.py
scisbi/simulator/GaussianMixtureSimulator.py
scisbi/simulator/GaussianSimulator.py
scisbi/simulator/LotkaVolterraSimulator.py
scisbi/simulator/TwoMoonSimulator.py
scisbi/simulator/__init__.py
scisbi/summary_statistic/__init__.py
scisbi-0.0.1.dist-info/licenses/LICENSE
scisbi-0.0.1.dist-info/METADATA
scisbi-0.0.1.dist-info/WHEEL
scisbi-0.0.1.dist-info/top_level.txt
scisbi-0.0.1.dist-info/RECORD
