Metadata-Version: 2.4
Name: scisbi
Version: 0.0.1
Summary: Simulation-based parameter inference library
Author-email: Csongor Horváth <csongor.horvath@it.uu.se>
License-Expression: Apache-2.0
Requires-Python: >=3.9
License-File: LICENSE
Dynamic: license-file
